Metadata-Version: 2.1
Name: GnB-probability-distributions
Version: 1.0
Summary: Gaussian and Binomial distributions
Author: Giovanni Cortes Morales
Author-email: giocortes19@gmail.com
